peer_measure/__init__.py
peer_measure-0.0.1.dist-info/LICENSE
peer_measure-0.0.1.dist-info/METADATA
peer_measure-0.0.1.dist-info/WHEEL
peer_measure-0.0.1.dist-info/top_level.txt
peer_measure-0.0.1.dist-info/RECORD
