Metadata-Version: 2.1
Name: peer_measure
Version: 0.0.1
Summary: Implementation of the measure Probability of Equal Expected Rank
Home-page: https://github.com/hltcoe/peer_measure
Author: Eugene Yang
Author-email: eugene.yang@jhu.edu
Requires-Python: >=3.8
License-File: LICENSE
Requires-Dist: numpy
Requires-Dist: scipy
Requires-Dist: ir-measures
